{
  "features": [
    {
      "type": "Feature",
      "properties": {
        "name": "Front General Store",
        "category": [
          "vintage",
          "thrift"
        ],
        "address": "143 Front St, Brooklyn, NY 11201"
      },
      "geometry": {
        "coordinates": [
          -73.987491,
          40.702498
        ],
        "type": "Point"
      },
      "id": "40b9da27247042ec1e884dadded15697"
    },
    {
      "type": "Feature",
      "properties": {
        "name": "Banh Mi Saigon",
        "category": [
          "vietnamese restaurant"
        ],
        "address": "198 Grand St, New York, NY 10013"
      },
      "geometry": {
        "coordinates": [
          -73.996726,
          40.719224
        ],
        "type": "Point"
      },
      "id": "8f5ac735ae5169566db222d07b51fc71"
    },
    {
      "type": "Feature",
      "properties": {
        "name": "Brooklyn Ball Factory",
        "category": [
          "cafe",
          "tea"
        ],
        "address": "95 Montrose Ave, Brooklyn, NY 11206"
      },
      "geometry": {
        "coordinates": [
          -73.945882,
          40.707214
        ],
        "type": "Point"
      },
      "id": "efdf24af201a6a797a4f1277c4a28df4"
    }
  ],
  "type": "FeatureCollection"
}